llm_distil/__init__.py
llm_distil/__version__.py
llm_distil/config.py
llm_distil/kd_trainer.py
llm_distil/losses.py
llm_distil/metrics.py
llm_distil/utils.py
llm_distil-0.1.0.dist-info/licenses/LICENSE
llm_distil-0.1.0.dist-info/METADATA
llm_distil-0.1.0.dist-info/WHEEL
llm_distil-0.1.0.dist-info/top_level.txt
llm_distil-0.1.0.dist-info/RECORD
