Metadata-Version: 2.4
Name: llm-distil
Version: 0.1.0
Summary: Knowledge Distillation for Large Language Models
Home-page: https://github.com/parmanu-lcs2/llm_distil
Author: Parmanu, LCS2, IIT Delhi
Author-email: 
License: Apache-2.0
Project-URL: Homepage, https://github.com/parmanu-lcs2/llm_distil
Project-URL: Bug Reports, https://github.com/parmanu-lcs2/llm_distil/issues
Project-URL: Source, https://github.com/parmanu-lcs2/llm_distil
Keywords: llm,knowledge-distillation,transformer,gpt,model-compression,nlp,deep-learning,pytorch
Classifier: Development Status :: 3 - Alpha
Classifier: Intended Audience :: Developers
Classifier: Intended Audience :: Science/Research
Classifier: License :: OSI Approved :: Apache Software License
Classifier: Programming Language :: Python :: 3
Classifier: Programming Language :: Python :: 3.8
Classifier: Programming Language :: Python :: 3.9
Classifier: Programming Language :: Python :: 3.10
Classifier: Programming Language :: Python :: 3.11
Classifier: Topic :: Scientific/Engineering :: Artificial Intelligence
Requires-Python: >=3.8
License-File: LICENSE
Requires-Dist: torch>=1.12.0
Requires-Dist: transformers>=4.30.0
Requires-Dist: datasets>=2.10.0
Requires-Dist: evaluate>=0.4.0
Requires-Dist: rouge-score>=0.1.2
Requires-Dist: tqdm>=4.65.0
Requires-Dist: numpy>=1.23.0
Requires-Dist: pandas>=1.3.0
Provides-Extra: dev
Requires-Dist: pytest>=7.0.0; extra == "dev"
Requires-Dist: black>=22.0.0; extra == "dev"
Requires-Dist: flake8>=4.0.0; extra == "dev"
Requires-Dist: jupyter>=1.0.0; extra == "dev"
Provides-Extra: logging
Requires-Dist: wandb>=0.15.0; extra == "logging"
Requires-Dist: tensorboard>=2.11.0; extra == "logging"
Dynamic: home-page
Dynamic: license-file
Dynamic: requires-python
